CONTRIBUTING.md
COPYING
COPYING.LESSER
MANIFEST.in
README.md
setup.cfg
setup.py
pycurious/__init__.py
pycurious/documentation.py
pycurious/download.py
pycurious/grid.py
pycurious/mapping.py
pycurious/optimise.py
pycurious.egg-info/PKG-INFO
pycurious.egg-info/SOURCES.txt
pycurious.egg-info/dependency_links.txt
pycurious.egg-info/requires.txt
pycurious.egg-info/top_level.txt
pycurious/Examples/0-StartHere.ipynb
pycurious/Examples/Notebooks/.ipynb_checkpoints/Ex1-Plot-power-spectrum-checkpoint.ipynb
pycurious/Examples/Notebooks/.ipynb_checkpoints/Ex2a-Compute-Curie-depth-Tanaka-approach-checkpoint.ipynb
pycurious/Examples/Notebooks/.ipynb_checkpoints/Ex2b-Compute-Curie-depth-Bouligand-approach-checkpoint.ipynb
pycurious/Examples/Notebooks/.ipynb_checkpoints/Ex3-Optimisation-routine-checkpoint.ipynb
pycurious/Examples/Notebooks/Bouligand/Ex1-Plot-power-spectrum.ipynb
pycurious/Examples/Notebooks/Bouligand/Ex2-Compute-Curie-depth.ipynb
pycurious/Examples/Notebooks/Bouligand/Ex3-Posing-the-inverse-problem.ipynb
pycurious/Examples/Notebooks/Bouligand/Ex4-Spatial-variation-of-Curie-depth.ipynb
pycurious/Examples/Notebooks/Bouligand/Ex5-Mapping-Curie-depth-EMAG2.ipynb
pycurious/Examples/Notebooks/Tanaka/Ex1-Plot-power-spectrum.ipynb
pycurious/Examples/Notebooks/Tanaka/Ex2-Compute-Curie-depth.ipynb
pycurious/Examples/Notebooks/Tanaka/Ex3-Parameter-exploration.ipynb
pycurious/Examples/data/test_mag_data.txt
src/cradon.c
src/cradon.h
src/cradon.pxd
src/radon.c
src/radon.pyx
tests/Bouligand_forward.py
tests/conftest.py
tests/test_0_imports.py
tests/test_grid.py
tests/test_optimise.py
tests/test_routines.py