Metadata-Version: 2.1
Name: pycurious
Version: 1.0.3
Summary: Python tool for computing the Curie depth from magnetic data
Home-page: https://github.com/brmather/pycurious
Author: Ben Mather
Author-email: brmather1@gmail.com
License: UNKNOWN
Platform: UNKNOWN
Classifier: Programming Language :: Python :: 2
Classifier: Programming Language :: Python :: 2.7
Classifier: Programming Language :: Python :: 3
Classifier: Programming Language :: Python :: 3.5
Classifier: Programming Language :: Python :: 3.6
Classifier: Programming Language :: Python :: 3.7
Requires-Python: >=2.7, >=3.5
